buf/__init__.py
buf/validate/__init__.py
buf/validate/validate_pb2.py
buf/validate/validate_pb2.pyi
buf/validate/validate_pb2_grpc.py
metalstackcloud/__init__.py
metalstackcloud/client.py
metalstackcloud/admin/__init__.py
metalstackcloud/admin/v1/__init__.py
metalstackcloud/admin/v1/audit_connecpy.py
metalstackcloud/admin/v1/audit_pb2.py
metalstackcloud/admin/v1/audit_pb2.pyi
metalstackcloud/admin/v1/audit_pb2_grpc.py
metalstackcloud/admin/v1/cluster_connecpy.py
metalstackcloud/admin/v1/cluster_pb2.py
metalstackcloud/admin/v1/cluster_pb2.pyi
metalstackcloud/admin/v1/cluster_pb2_grpc.py
metalstackcloud/admin/v1/machine_pb2.py
metalstackcloud/admin/v1/machine_pb2.pyi
metalstackcloud/admin/v1/machine_pb2_grpc.py
metalstackcloud/admin/v1/payment_connecpy.py
metalstackcloud/admin/v1/payment_pb2.py
metalstackcloud/admin/v1/payment_pb2.pyi
metalstackcloud/admin/v1/payment_pb2_grpc.py
metalstackcloud/admin/v1/project_connecpy.py
metalstackcloud/admin/v1/project_pb2.py
metalstackcloud/admin/v1/project_pb2.pyi
metalstackcloud/admin/v1/project_pb2_grpc.py
metalstackcloud/admin/v1/storage_connecpy.py
metalstackcloud/admin/v1/storage_pb2.py
metalstackcloud/admin/v1/storage_pb2.pyi
metalstackcloud/admin/v1/storage_pb2_grpc.py
metalstackcloud/admin/v1/tenant_connecpy.py
metalstackcloud/admin/v1/tenant_pb2.py
metalstackcloud/admin/v1/tenant_pb2.pyi
metalstackcloud/admin/v1/tenant_pb2_grpc.py
metalstackcloud/admin/v1/token_connecpy.py
metalstackcloud/admin/v1/token_pb2.py
metalstackcloud/admin/v1/token_pb2.pyi
metalstackcloud/admin/v1/token_pb2_grpc.py
metalstackcloud/api/__init__.py
metalstackcloud/api/v1/__init__.py
metalstackcloud/api/v1/asset_connecpy.py
metalstackcloud/api/v1/asset_pb2.py
metalstackcloud/api/v1/asset_pb2.pyi
metalstackcloud/api/v1/asset_pb2_grpc.py
metalstackcloud/api/v1/audit_connecpy.py
metalstackcloud/api/v1/audit_pb2.py
metalstackcloud/api/v1/audit_pb2.pyi
metalstackcloud/api/v1/audit_pb2_grpc.py
metalstackcloud/api/v1/cluster_connecpy.py
metalstack_cloud-0.16.0.dist-info/METADATA
metalstack_cloud-0.16.0.dist-info/WHEEL
metalstack_cloud-0.16.0.dist-info/top_level.txt
metalstack_cloud-0.16.0.dist-info/RECORD
