Metadata-Version: 2.4
Name: metalstack.cloud
Version: 0.16.0
Summary: Python API client for metalstack.cloud api
Home-page: https://github.com/metal-stack-cloud/api
Author: metalstack.cloud authors
License: MIT
Keywords: metalstack.cloud
Classifier: Intended Audience :: Developers
Classifier: Natural Language :: English
Classifier: Operating System :: POSIX
Classifier: Programming Language :: Python :: 3
Classifier: Programming Language :: Python :: 3.11
Classifier: Programming Language :: Python :: 3.12
Classifier: Programming Language :: Python :: 3.13
Requires-Dist: connecpy>=1.5.2
Dynamic: author
Dynamic: classifier
Dynamic: description
Dynamic: home-page
Dynamic: keywords
Dynamic: license
Dynamic: requires-dist
Dynamic: summary
